Workbook
Name \0: '[1]PNT-QUOT-#3'!#REF!
Name \a: #REF!
Name \b: #N/A
Name \c: #REF!
Name \d: #N/A
Name \e: #N/A
Name \f: #REF!
Name \h: #REF!
Name \i: #N/A
Name \j: #N/A
Name \k: #N/A
Name \l: #REF!
Name \m: #N/A
Name \n: #N/A
Name \o: #N/A
Name \p: #N/A
Name \q: #N/A
Name \r: #REF!
Name \s: #REF!
Name \t: #N/A
Name \u: #N/A
Name \v: #REF!
Name \w: #N/A
Name \x: #REF!
Name \z: #N/A
Name _: [2]PRICE!#REF!
Name __: [2]PRICE!#REF!
Name ___: [2]PRICE!#REF!
Name ____: [2]PRICE!#REF!
Name _____: [2]PRICE!#REF!
Name ______: [2]PRICE!#REF!
Name _______: [2]PRICE!#REF!
Name ________: [2]PRICE!#REF!
Name _________: [2]PRICE!#REF!
Name __________: [2]PRICE!#REF!
Name ___________: [2]PRICE!#REF!
Name _____________: [2]PRICE!#REF!
Name _______________: [2]PRICE!#REF!
Name _________________: [2]PRICE!#REF!
Name ___________________: [2]PRICE!#REF!
Name ____________________: [2]PRICE!#REF!
Name ________________________: [2]PRICE!#REF!
Name ____________________________________________sub1: #REF!
Name ___________________________________________DUM2: [3]stair!#REF!
Name ___________________________________________DUM3: [3]stair!#REF!
Name ___________________________________________DUM4: [3]stair!#REF!
Name ___________________________________________LL1: [3]stair!#REF!
Name ___________________________________________LL3: [3]stair!#REF!
Name ___________________________________________NC1: #REF!
Name ___________________________________________NC2: [4]STRUCTURE!#REF!
Name ___________________________________________NC3: [4]STRUCTURE!#REF!
Name ___________________________________________RU1: [3]stair!#REF!
Name ___________________________________________RU2: [3]stair!#REF!
Name ___________________________________________sub1: #REF!
Name ___________________________________________TP2: #REF!
Name ___________________________________________WL1: [3]stair!#REF!
Name ___________________________________________WL2: [3]stair!#REF!
Name ___________________________________________WU1: [3]stair!#REF!
Name ___________________________________________WU3: [3]stair!#REF!
Name __________________________________________DUM2: [3]stair!#REF!

Sheet SUM
C1: Job : | D1: ='Detail '!D1 -> งานติดตั้งระบบแจ้งเหตุเพลิงไหม้ โรงฉ่ำวัตถุดิบ | G1: CPF (Thailand) Public Company
C2: Location : | D2: ='Detail '!D2 -> โรงงานผลิตอาหารสัตว์บกโคกกรวด | G2: 1 C.P. Tower 2 (Fortune Town Bldg.),
C3: Owner : | D3: บมจ.ซีพีเอฟ (ประเทศไทย) | G3: 11st Floor Ratchadapisek Rd.,
C4: Revision : | D4: 1 | G4: Dindaeng Bangkok 10400, THAILAND
C5: Date : | D5: 46072
C6: บริษัทxxx
A8: ลำดับ | B8: รายการ | C8: ปริมาณวัสดุ | E8: ค่าวัสดุ | F8: ค่าแรง | G8: รวมราคา | H8: หมายเหตุ
C9: ปริมาณ | D9: หน่วย | E9: บาท | F9: บาท
A10: 1 | B10: ='Detail '!B11 -> โรงเก็บเชื่อเพลิง+หอพกชั้น2 | C10: 1 | D10: Lot | E10: ='Detail '!F19 -> 0 | F10: ='Detail '!H19 -> 0 | G10: ='Detail '!I19 -> 0
A11: 2 | B11: ='Detail '!B21 -> วิศวกรรม | C11: 1 | D11: Lot | E11: ='Detail '!F28 -> 0 | F11: ='Detail '!H28 -> 0 | G11: ='Detail '!I28 -> 0
A12: 3 | B12: ='Detail '!B30 -> ห้อง Battery อสร. | C12: 1 | D12: Lot | E12: ='Detail '!F37 -> 0 | F12: ='Detail '!H37 -> 0 | G12: ='Detail '!I37 -> 0
A13: 4 | B13: ='Detail '!B39 -> ห้องควบคุมโรบอท | C13: 1 | D13: Lot | E13: ='Detail '!F47 -> 0 | F13: ='Detail '!H47 -> 0 | G13: ='Detail '!I47 -> 0
A14: 5 | B14: ='Detail '!B49 -> ห้องเก็บเอกสาร | C14: 1 | D14: Lot | E14: ='Detail '!F56 -> 0 | F14: ='Detail '!H56 -> 0 | G14: ='Detail '!I56 -> 0 | J14: Natchaya Khamsiyaphorn (Khaning)
A15: 6 | B15: ='Detail '!B58 -> Office คลัง+ Office จป. | C15: 1 | D15: Lot | E15: ='Detail '!F65 -> 0 | F15: ='Detail '!H65 -> 0 | G15: ='Detail '!I65 -> 0 | J15: ณัฐชยา คำสิยาภรณ์ (คะนิ้ง)
A16: 7 | B16: ='Detail '!B67 -> ห้อง Inverter | C16: 1 | D16: Lot | E16: ='Detail '!F74 -> 0 | F16: ='Detail '!H74 -> 0 | G16: ='Detail '!I74 -> 0 | J16: Account Executive
A17: 8 | B17: ='Detail '!B76 -> ห้องเก็บวัตถุดิบ | C17: 1 | D17: Lot | E17: ='Detail '!F83 -> 0 | F17: ='Detail '!H83 -> 0 | G17: ='Detail '!I83 -> 0 | J17: M : 06-3918-3474
A18: 9 | B18: ='Detail '!B85 -> ห้องควบคุมผลิต ชั้น2 | C18: 1 | D18: Lot | E18: ='Detail '!F93 -> 0 | F18: ='Detail '!H93 -> 0 | G18: ='Detail '!I93 -> 0 | J18: E-mail : natchaya.kha@pantavanij.com
A19: 10 | B19: ='Detail '!B95 -> ห้องไฟฟ้าอาคารผลิต ชั้น2 | C19: 1 | D19: Lot | E19: ='Detail '!F102 -> 0 | F19: ='Detail '!H102 -> 0 | G19: ='Detail '!I102 -> 0
A20: 11 | B20: ='Detail '!B104 -> ห้องไฟฟ้าอาคารผลิต ชั้น1 | C20: 1 | D20: Lot | E20: ='Detail '!F111 -> 0 | F20: ='Detail '!H111 -> 0 | G20: ='Detail '!I111 -> 0
A21: 12 | B21: ='Detail '!B113 -> ห้องน้ำยาเอนไซม์ | C21: 1 | D21: Lot | E21: ='Detail '!F120 -> 0 | F21: ='Detail '!H120 -> 0 | G21: ='Detail '!I120 -> 0
A22: 13 | B22: ='Detail '!B122 -> ห้องหม้อแปลง | C22: 1 | D22: Lot | E22: ='Detail '!F129 -> 0 | F22: ='Detail '!H129 -> 0 | G22: ='Detail '!I129 -> 0
A23: 14 | B23: ='Detail '!B131 -> Other | C23: 1 | D23: Lot | E23: ='Detail '!F138 -> 0 | F23: ='Detail '!H138 -> 0 | G23: ='Detail '!I138 -> 0
B25: SUM 1-14 | G25: ='Detail '!I140 -> 0
B26: Overhead & Profit | G26: ='Detail '!I141 -> 0
B27: SUM | G27: ='Detail '!I142 -> 0
B28: Vat 7% | G28: ='Detail '!I143 -> 0
B29: Total (THB) | G29: ='Detail '!I144 -> 0
A32: หมายเหตุ : | B32: ชื่อ-นามสกุล (ผู้เสนอราคา/ผู้เข้าประมูล) :
B33: เบอร์ติดต่อ :
B34: E-mail :
A36: Note:

Sheet Detail 
C1: Job : | D1: งานติดตั้งระบบแจ้งเหตุเพลิงไหม้ โรงฉ่ำวัตถุดิบ | G1: CPF (Thailand) Public Company
C2: Location : | D2: โรงงานผลิตอาหารสัตว์บกโคกกรวด | G2: 1 C.P. Tower 2 (Fortune Town Bldg.),
C3: Owner : | D3: บมจ.ซีพีเอฟ (ประเทศไทย) | G3: 11st Floor Ratchadapisek Rd.,
C4: Revision : | D4: 1 | G4: Dindaeng Bangkok 10400,
C5: Date : | D5: 46072 | G5: THAILAND
C6: =SUM!C6 -> บริษัทxxx
A8: ลำดับ | B8: รายการ | C8: ปริมาณวัสดุ | E8: ค่าวัสดุ | G8: ค่าแรง | I8: รวมราคา | J8: หมายเหตุ
C9: ปริมาณ | D9: หน่วย | E9: บาท | F9: รวม | G9: บาท | H9: รวม
A11: 1 | B11: โรงเก็บเชื่อเพลิง+หอพกชั้น2
B12: Heat detector explosion proof | C12: 3 | D12: set | F12: =C12*E12 -> 0 | H12: =C12*G12 -> 0 | I12: =H12+F12 -> 0
B13: Smoke detector | C13: 1 | D13: ea | F13: =C13*E13 -> 0 | H13: =C13*G13 -> 0 | I13: =H13+F13 -> 0
B14: Installation work | C14: 1 | D14: lot | F14: =C14*E14 -> 0 | H14: =C14*G14 -> 0 | I14: =H14+F14 -> 0
B15: - IMC Conduit 3/4
B16: - IEC01 Copper 1x1.5 Sq.mm.
B17: - Flexible conduit and fitting
B19: SUM 1 | F19: =SUM(F12:F16) -> 0 | H19: =SUM(H12:H16) -> 0 | I19: =SUM(I12:I17) -> 0
A21: 2 | B21: วิศวกรรม
B22: Smoke detector | C22: 5 | D22: ea | F22: =C22*E22 -> 0 | H22: =C22*G22 -> 0 | I22: =H22+F22 -> 0
B23: Installation work | C23: 1 | D23: lot | F23: =C23*E23 -> 0 | H23: =C23*G23 -> 0 | I23: =H23+F23 -> 0
B24: - IMC Conduit 3/4
B25: - IEC01 Copper 1x1.5 Sq.mm.
B26: - Flexible conduit and fitting
B28: SUM 2 | F28: =SUM(F22:F27) -> 0 | H28: =SUM(H22:H27) -> 0 | I28: =SUM(I22:I27) -> 0
A30: 3 | B30: ห้อง Battery อสร.
B31: Heat detector | C31: 6 | D31: ea | F31: =C31*E31 -> 0 | H31: =C31*G31 -> 0 | I31: =H31+F31 -> 0
B32: Installation work | C32: 1 | D32: lot | F32: =C32*E32 -> 0 | H32: =C32*G32 -> 0 | I32: =H32+F32 -> 0
B33: - IMC Conduit 3/4
B34: - IEC01 Copper 1x1.5 Sq.mm.
B35: - Flexible conduit and fitting
B37: SUM 3 | F37: =SUM(F31:F36) -> 0 | H37: =SUM(H31:H36) -> 0 | I37: =SUM(I31:I36) -> 0
A39: 4 | B39: ห้องควบคุมโรบอท
B40: Heat detector | C40: 1 | D40: ea | F40: =C40*E40 -> 0 | H40: =C40*G40 -> 0 | I40: =H40+F40 -> 0
B41: Installation work | C41: 1 | D41: lot | F41: =C41*E41 -> 0 | H41: =C41*G41 -> 0 | I41: =H41+F41 -> 0
B42: - IMC Conduit 3/4
B43: - IEC01 Copper 1x1.5 Sq.mm.
B44: - Flexible conduit and fitting
B45: งานฝังท่อ | C45: 1 | D45: lot | F45: =C45*E45 -> 0 | H45: =C45*G45 -> 0 | I45: =H45+F45 -> 0
B47: SUM 4 | F47: =SUM(F40:F46) -> 0 | H47: =SUM(H40:H46) -> 0 | I47: =SUM(I40:I46) -> 0
A49: 5 | B49: ห้องเก็บเอกสาร
B50: Smoke detector | C50: 1 | D50: ea | F50: =C50*E50 -> 0 | H50: =C50*G50 -> 0 | I50: =H50+F50 -> 0
B51: Installation work | C51: 1 | D51: lot | F51: =C51*E51 -> 0 | H51: =C51*G51 -> 0 | I51: =H51+F51 -> 0
B52: - IMC Conduit 3/4
B53: - IEC01 Copper 1x1.5 Sq.mm.
B54: - Flexible conduit and fitting
B56: SUM 5 | F56: =SUM(F50:F55) -> 0 | H56: =SUM(H50:H55) -> 0 | I56: =SUM(I50:I55) -> 0
A58: 6 | B58: Office คลัง+ Office จป.
B59: Smoke detector | C59: 2 | D59: ea | F59: =C59*E59 -> 0 | H59: =C59*G59 -> 0 | I59: =H59+F59 -> 0
B60: Installation work | C60: 1 | D60: lot | F60: =C60*E60 -> 0 | H60: =C60*G60 -> 0 | I60: =H60+F60 -> 0
B61: - IMC Conduit 3/4
B62: - IEC01 Copper 1x1.5 Sq.mm.
B63: - Flexible conduit and fitting
B65: SUM 6 | F65: =SUM(F59:F64) -> 0 | H65: =SUM(H59:H64) -> 0 | I65: =SUM(I59:I64) -> 0
A67: 7 | B67: ห้อง Inverter
B68: Heat detector | C68: 4 | D68: ea | F68: =C68*E68 -> 0 | H68: =C68*G68 -> 0 | I68: =H68+F68 -> 0
B69: Installation work | C69: 1 | D69: lot | F69: =C69*E69 -> 0 | H69: =C69*G69 -> 0 | I69: =H69+F69 -> 0
B70: - IMC Conduit 3/4
B71: - IEC01 Copper 1x1.5 Sq.mm.
B72: - Flexible conduit and fitting
B74: SUM 7 | F74: =SUM(F68:F73) -> 0 | H74: =SUM(H68:H73) -> 0 | I74: =SUM(I68:I73) -> 0
A76: 8 | B76: ห้องเก็บวัตถุดิบ
B77: Heat detector | C77: 4 | D77: ea | F77: =C77*E77 -> 0 | H77: =C77*G77 -> 0 | I77: =H77+F77 -> 0
B78: Installation work | C78: 1 | D78: lot | F78: =C78*E78 -> 0 | H78: =C78*G78 -> 0 | I78: =H78+F78 -> 0
B79: - IMC Conduit 3/4
B80: - IEC01 Copper 1x1.5 Sq.mm.
B81: - Flexible conduit and fitting
B83: SUM 8 | F83: =SUM(F77:F82) -> 0 | H83: =SUM(H77:H82) -> 0 | I83: =SUM(I77:I82) -> 0
A85: 9 | B85: ห้องควบคุมผลิต ชั้น2
B86: Smoke detector | C86: 3 | D86: ea | F86: =C86*E86 -> 0 | H86: =C86*G86 -> 0 | I86: =H86+F86 -> 0
B87: Installation work | C87: 1 | D87: lot | F87: =C87*E87 -> 0 | H87: =C87*G87 -> 0 | I87: =H87+F87 -> 0
B88: - IMC Conduit 3/4
B89: - IEC01 Copper 1x1.5 Sq.mm.
B90: - Flexible conduit and fitting
B91: งานรื้อถอนอุปกรณ์นอกห้อง | C91: 1 | D91: lot | F91: =C91*E91 -> 0 | H91: =C91*G91 -> 0 | I91: =H91+F91 -> 0
B93: SUM 9 | F93: =SUM(F86:F92) -> 0 | H93: =SUM(H86:H92) -> 0 | I93: =SUM(I86:I92) -> 0
A95: 10 | B95: ห้องไฟฟ้าอาคารผลิต ชั้น2
B96: Smoke detector | C96: 1 | D96: ea | F96: =C96*E96 -> 0 | H96: =C96*G96 -> 0 | I96: =H96+F96 -> 0
B97: Installation work | C97: 1 | D97: lot | F97: =C97*E97 -> 0 | H97: =C97*G97 -> 0 | I97: =H97+F97 -> 0
B98: - IMC Conduit 3/4
B99: - IEC01 Copper 1x1.5 Sq.mm.
B100: - Flexible conduit and fitting
B102: SUM 10 | F102: =SUM(F96:F101) -> 0 | H102: =SUM(H96:H101) -> 0 | I102: =SUM(I96:I101) -> 0
A104: 11 | B104: ห้องไฟฟ้าอาคารผลิต ชั้น1
B105: Smoke detector | C105: 1 | D105: ea | F105: =C105*E105 -> 0 | H105: =C105*G105 -> 0 | I105: =H105+F105 -> 0
B106: Installation work | C106: 1 | D106: lot | F106: =C106*E106 -> 0 | H106: =C106*G106 -> 0 | I106: =H106+F106 -> 0
B107: - IMC Conduit 3/4
B108: - IEC01 Copper 1x1.5 Sq.mm.
B109: - Flexible conduit and fitting
B111: SUM 11 | F111: =SUM(F105:F110) -> 0 | H111: =SUM(H105:H110) -> 0 | I111: =SUM(I105:I110) -> 0
A113: 12 | B113: ห้องน้ำยาเอนไซม์
B114: Smoke detector | C114: 1 | D114: ea | F114: =C114*E114 -> 0 | H114: =C114*G114 -> 0 | I114: =H114+F114 -> 0
B115: Installation work | C115: 1 | D115: lot | F115: =C115*E115 -> 0 | H115: =C115*G115 -> 0 | I115: =H115+F115 -> 0
B116: - IMC Conduit 3/4
B117: - IEC01 Copper 1x1.5 Sq.mm.
B118: - Flexible conduit and fitting
B120: SUM 12 | F120: =SUM(F114:F119) -> 0 | H120: =SUM(H114:H119) -> 0 | I120: =SUM(I114:I119) -> 0
A122: 13 | B122: ห้องหม้อแปลง
B123: Heat detector | C123: 2 | D123: ea | F123: =C123*E123 -> 0 | H123: =C123*G123 -> 0 | I123: =H123+F123 -> 0
B124: Installation work | C124: 1 | D124: lot | F124: =C124*E124 -> 0 | H124: =C124*G124 -> 0 | I124: =H124+F124 -> 0
B125: - IMC Conduit 3/4
B126: - IEC01 Copper 1x1.5 Sq.mm.
...
